{
 "actions": [],
 "allow_rename": 1,
 "autoname": "TB.#####",
 "creation": "2026-01-13 11:56:18.465028",
 "doctype": "DocType",
 "editable_grid": 1,
 "engine": "InnoDB",
 "field_order": [
  "date",
  "from",
  "to",
  "reason"
 ],
 "fields": [
  {
   "default": "Today",
   "fieldname": "date",
   "fieldtype": "Date",
   "in_list_view": 1,
   "label": "Date"
  },
  {
   "fieldname": "from",
   "fieldtype": "Data",
   "in_list_view": 1,
   "label": "From"
  },
  {
   "fieldname": "to",
   "fieldtype": "Data",
   "in_list_view": 1,
   "label": "To"
  },
  {
   "fieldname": "reason",
   "fieldtype": "Data",
   "in_list_view": 1,
   "label": "Reason"
  }
 ],
 "index_web_pages_for_search": 1,
 "istable": 1,
 "links": [],
 "modified": "2026-01-13 11:56:18.465028",
 "modified_by": "Administrator",
 "module": "Veterinary Management",
 "name": "Transfer Bed",
 "naming_rule": "Expression (old style)",
 "owner": "Administrator",
 "permissions": [],
 "row_format": "Dynamic",
 "sort_field": "modified",
 "sort_order": "DESC",
 "states": []
}